plainform.py
plainform-0.10.0.dist-info/DESCRIPTION.rst
plainform-0.10.0.dist-info/METADATA
plainform-0.10.0.dist-info/RECORD
plainform-0.10.0.dist-info/WHEEL
plainform-0.10.0.dist-info/metadata.json
plainform-0.10.0.dist-info/top_level.txt
